Metadata-Version: 2.1
Name: firebotpy
Version: 3.0
Summary: Python library to connect to Firebots API
Home-page: https://github.com/whatupcraig/Firebotpy
Author: DadTheGam3r
Author-email: bailey_craig@me.com
License: MIT
Download-URL: https://github.com/whatupcraig/Firebotpy.git
Keywords: firebot,api,twitch
Platform: UNKNOWN
Classifier: Development Status :: 5 - Production/Stable
Classifier: Intended Audience :: Developers
Classifier: License :: OSI Approved :: MIT License
Classifier: Programming Language :: Python :: 3
Classifier: Programming Language :: Python :: 3.4
Classifier: Programming Language :: Python :: 3.5
Classifier: Programming Language :: Python :: 3.6
Classifier: Programming Language :: Python :: 3.7
Classifier: Programming Language :: Python :: 3.8
Classifier: Programming Language :: Python :: 3.9
License-File: LICENCE.txt
